CHANGES.txt
README.txt
example-buildout.cfg
setup.py
src/z3c/__init__.py
src/z3c.recipe.depgraph.egg-info/PKG-INFO
src/z3c.recipe.depgraph.egg-info/SOURCES.txt
src/z3c.recipe.depgraph.egg-info/dependency_links.txt
src/z3c.recipe.depgraph.egg-info/entry_points.txt
src/z3c.recipe.depgraph.egg-info/namespace_packages.txt
src/z3c.recipe.depgraph.egg-info/not-zip-safe
src/z3c.recipe.depgraph.egg-info/requires.txt
src/z3c.recipe.depgraph.egg-info/top_level.txt
src/z3c/recipe/__init__.py
src/z3c/recipe/depgraph/__init__.py
src/z3c/recipe/depgraph/recipe.py
src/z3c/recipe/depgraph/runner.py