Metadata-Version: 1.0
Name: z3c.recipe.depgraph
Version: 0.3
Summary: Buildout recipe to generate dependency graphs.
Home-page: http://pypi.python.org/pypi/z3c.recipe.depgraph
Author: Zope Community
Author-email: zope-dev@zope.org
License: ZPL 2.1
Keywords: egg dependency
Platform: UNKNOWN
Classifier: Intended Audience :: Developers
Classifier: License :: OSI Approved :: Zope Public License
Classifier: Programming Language :: Python
Classifier: Operating System :: OS Independent
